google_ime_skk_py/__init__.py
google_ime_skk_py/__version__.py
google_ime_skk_py/google_ime_skk.py
google_ime_skk_py-0.0.4.dist-info/LICENSE.txt
google_ime_skk_py-0.0.4.dist-info/METADATA
google_ime_skk_py-0.0.4.dist-info/WHEEL
google_ime_skk_py-0.0.4.dist-info/entry_points.txt
google_ime_skk_py-0.0.4.dist-info/top_level.txt
google_ime_skk_py-0.0.4.dist-info/RECORD
