Metadata-Version: 2.1
Name: google-ime-skk-py
Version: 0.0.4
Summary: Google IME SKK server written in Python
Home-page: https://github.com/chaploud/google-ime-skk-py
Author: chaploud
License: MIT
Platform: UNKNOWN
Requires-Python: >=3.6
License-File: LICENSE.txt
